[
    {
        "% Change": "8.22222",
        "LTP": "243.50",
        "Symbol": "MEGA"
    },
    {
        "% Change": "3.52941",
        "LTP": "8.80",
        "Symbol": "NIBSF2"
    },
    {
        "% Change": "2.6601",
        "LTP": "1042.00",
        "Symbol": "GMFBS"
    },
    {
        "% Change": "2.04646",
        "LTP": "369.00",
        "Symbol": "BPCL"
    },
    {
        "% Change": "1.99231",
        "LTP": "19089.90",
        "Symbol": "UNL"
    },
    {
        "% Change": "1.98377",
        "LTP": "113.10",
        "Symbol": "BHL"
    },
    {
        "% Change": "1.95853",
        "LTP": "8.85",
        "Symbol": "PSF"
    },
    {
        "% Change": "1.95122",
        "LTP": "627.00",
        "Symbol": "ALICL"
    },
    {
        "% Change": "1.93798",
        "LTP": "1315.00",
        "Symbol": "GILB"
    },
    {
        "% Change": "1.91083",
        "LTP": "960.00",
        "Symbol": "MKLB"
    },
    {
        "% Change": "1.9037",
        "LTP": "9.10",
        "Symbol": "KEF"
    },
    {
        "% Change": "1.87354",
        "LTP": "8.70",
        "Symbol": "NBF3"
    },
    {
        "% Change": "1.75115",
        "LTP": "220.80",
        "Symbol": "KBL"
    },
    {
        "% Change": "1.74419",
        "LTP": "10.50",
        "Symbol": "NEF"
    },
    {
        "% Change": "1.73866",
        "LTP": "3745.00",
        "Symbol": "BBC"
    },
    {
        "% Change": "1.7257",
        "LTP": "11.20",
        "Symbol": "NIBLPF"
    },
    {
        "% Change": "1.58311",
        "LTP": "385.00",
        "Symbol": "EDBL"
    },
    {
        "% Change": "1.52941",
        "LTP": "258.90",
        "Symbol": "PRVU"
    },
    {
        "% Change": "1.45455",
        "LTP": "279.00",
        "Symbol": "UMHL"
    },
    {
        "% Change": "1.44783",
        "LTP": "1016.00",
        "Symbol": "RULB"
    },
    {
        "% Change": "1.38146",
        "LTP": "2275.00",
        "Symbol": "JALPA"
    },
    {
        "% Change": "1.22283",
        "LTP": "745.00",
        "Symbol": "CHDC"
    },
    {
        "% Change": "1.13725",
        "LTP": "257.90",
        "Symbol": "UPCL"
    },
    {
        "% Change": "1.08932",
        "LTP": "464.00",
        "Symbol": "MNBBL"
    },
    {
        "% Change": "1.08025",
        "LTP": "655.00",
        "Symbol": "NLICL"
    },
    {
        "% Change": "1.04408",
        "LTP": "871.00",
        "Symbol": "NLIC"
    },
    {
        "% Change": "1.03834",
        "LTP": "12.65",
        "Symbol": "NMB50"
    },
    {
        "% Change": "0.990099",
        "LTP": "306.00",
        "Symbol": "NBL"
    },
    {
        "% Change": "0.961538",
        "LTP": "630.00",
        "Symbol": "NLG"
    },
    {
        "% Change": "0.952381",
        "LTP": "212.00",
        "Symbol": "CBL"
    },
    {
        "% Change": "0.883002",
        "LTP": "457.00",
        "Symbol": "SGI"
    },
    {
        "% Change": "0.875657",
        "LTP": "288.00",
        "Symbol": "NIFRA"
    },
    {
        "% Change": "0.854701",
        "LTP": "236.00",
        "Symbol": "BOKL"
    },
    {
        "% Change": "0.852878",
        "LTP": "473.00",
        "Symbol": "MFIL"
    },
    {
        "% Change": "0.844278",
        "LTP": "1075.00",
        "Symbol": "SICL"
    },
    {
        "% Change": "0.836645",
        "LTP": "482.10",
        "Symbol": "GIC"
    },
    {
        "% Change": "0.831933",
        "LTP": "1199.90",
        "Symbol": "KMCDB"
    },
    {
        "% Change": "0.753769",
        "LTP": "401.00",
        "Symbol": "BFC"
    },
    {
        "% Change": "0.71649",
        "LTP": "2937.90",
        "Symbol": "JBLB"
    },
    {
        "% Change": "0.68297",
        "LTP": "914.00",
        "Symbol": "NSLB"
    },
    {
        "% Change": "0.645161",
        "LTP": "780.00",
        "Symbol": "NICA"
    },
    {
        "% Change": "0.626959",
        "LTP": "321.00",
        "Symbol": "RLFL"
    },
    {
        "% Change": "0.616683",
        "LTP": "310.00",
        "Symbol": "NFS"
    },
    {
        "% Change": "0.601132",
        "LTP": "284.50",
        "Symbol": "NMB"
    },
    {
        "% Change": "0.591549",
        "LTP": "357.10",
        "Symbol": "NYADI"
    },
    {
        "% Change": "0.580552",
        "LTP": "207.90",
        "Symbol": "CCBL"
    },
    {
        "% Change": "0.550964",
        "LTP": "365.00",
        "Symbol": "ADBL"
    },
    {
        "% Change": "0.541436",
        "LTP": "909.90",
        "Symbol": "ACLBSL"
    },
    {
        "% Change": "0.502857",
        "LTP": "439.70",
        "Symbol": "CHCL"
    },
    {
        "% Change": "0.492881",
        "LTP": "367.00",
        "Symbol": "SHPC"
    }
]