[
    {
        "% Change": "-3.92",
        "LTP": "342.80",
        "Symbol": "MEGA"
    },
    {
        "% Change": "-3.89",
        "LTP": "961.10",
        "Symbol": "PBD85"
    },
    {
        "% Change": "-3.09",
        "LTP": "18800.00",
        "Symbol": "UNL"
    },
    {
        "% Change": "-2.00",
        "LTP": "1024.10",
        "Symbol": "ADBLD83"
    },
    {
        "% Change": "-1.79",
        "LTP": "1041.00",
        "Symbol": "NICAD8283"
    },
    {
        "% Change": "-1.71",
        "LTP": "907.50",
        "Symbol": "GUFL"
    },
    {
        "% Change": "-1.70",
        "LTP": "1617.10",
        "Symbol": "MLBBL"
    },
    {
        "% Change": "-1.65",
        "LTP": "298.00",
        "Symbol": "KBL"
    },
    {
        "% Change": "-1.57",
        "LTP": "11.25",
        "Symbol": "NICGF"
    },
    {
        "% Change": "-1.45",
        "LTP": "11.56",
        "Symbol": "NIBSF1"
    },
    {
        "% Change": "-1.44",
        "LTP": "1030.00",
        "Symbol": "SBIBD86"
    },
    {
        "% Change": "-1.30",
        "LTP": "1120.20",
        "Symbol": "GWFD83"
    },
    {
        "% Change": "-1.02",
        "LTP": "594.00",
        "Symbol": "EDBL"
    },
    {
        "% Change": "-0.95",
        "LTP": "832.00",
        "Symbol": "NABBC"
    },
    {
        "% Change": "-0.95",
        "LTP": "9.41",
        "Symbol": "NIBSF2"
    },
    {
        "% Change": "-0.31",
        "LTP": "957.00",
        "Symbol": "LBLD88"
    },
    {
        "% Change": "-0.28",
        "LTP": "357.00",
        "Symbol": "SBI"
    },
    {
        "% Change": "-0.20",
        "LTP": "9.88",
        "Symbol": "LEMF"
    },
    {
        "% Change": "-0.19",
        "LTP": "527.00",
        "Symbol": "SCB"
    },
    {
        "% Change": "-0.17",
        "LTP": "2890.00",
        "Symbol": "JSLBB"
    },
    {
        "% Change": "-0.15",
        "LTP": "1295.00",
        "Symbol": "DDBL"
    }
]